<?xml version='1.0' encoding='UTF-8'?>
<GTA3Script Version="2.0">
  <Commands>
    <Command Name="IS_MISSION_SKIP">
      <Params>
        <Param Type="OUTPUT_INT"/>
      </Params>
    </Command>
    <Command Name="SET_IN_AMMUNATION">
      <Params>
        <Param Type="INPUT_INT"/>
      </Params>
    </Command>
    <Command Name="DO_SAVE_GAME">
      <Params>
        <Param Type="INPUT_INT"/>
      </Params>
    </Command>
    <Command Name="IS_RETRY">
      <Params>
        <Param Type="OUTPUT_INT"/>
      </Params>
    </Command>
    <Command Name="DUMMY"/>
    <Command Name="MARK_CUTSCENE_START"/>
    <Command Name="MARK_CUTSCENE_END"/>
    <Command Name="CUTSCENE_SCROLL"/>
    <Command Name="SET_LVAR_TEXT_LABEL_TO_LVAR_TEXT_LABEL">
      <Params>
        <Param Type="LVAR_TEXT_LABEL"/>
        <Param Type="LVAR_TEXT_LABEL"/>
      </Params>
    </Command>
    <Command Name="SET_VAR_TEXT_LABEL_TO_LVAR_TEXT_LABEL">
      <Params>
        <Param Type="VAR_TEXT_LABEL"/>
        <Param Type="LVAR_TEXT_LABEL"/>
      </Params>
    </Command>
    <Command Name="SET_LVAR_TEXT_LABEL_TO_VAR_TEXT_LABEL">
      <Params>
        <Param Type="LVAR_TEXT_LABEL"/>
        <Param Type="VAR_TEXT_LABEL"/>
      </Params>
    </Command>
    <Command Name="VAR_TEXT_LABEL">
      <Params>
        <Param Type="VAR_TEXT_LABEL"/>
        <Param Type="VAR_TEXT_LABEL_OPT"/>
      </Params>
    </Command>
    <Command Name="LVAR_TEXT_LABEL">
      <Params>
        <Param Type="LVAR_TEXT_LABEL"/>
        <Param Type="LVAR_TEXT_LABEL_OPT"/>
      </Params>
    </Command>
    <Command Name="IS_TEXT_LABEL_VAR_EQUAL_TO_TEXT_LABEL">
      <Params>
        <Param Type="VAR_TEXT_LABEL"/>
        <Param Type="TEXT_LABEL"/>
      </Params>
    </Command>
    <Command Name="IS_TEXT_LABEL_LVAR_EQUAL_TO_TEXT_LABEL">
      <Params>
        <Param Type="LVAR_TEXT_LABEL"/>
        <Param Type="TEXT_LABEL"/>
      </Params>
    </Command>
    <Command Name="IS_TEXT_LABEL_VAR_EQUAL_TO_TEXT_LABEL_VAR">
      <Params>
        <Param Type="VAR_TEXT_LABEL"/>
        <Param Type="VAR_TEXT_LABEL"/>
      </Params>
    </Command>
    <Command Name="IS_TEXT_LABEL_LVAR_EQUAL_TO_TEXT_LABEL_LVAR">
      <Params>
        <Param Type="LVAR_TEXT_LABEL"/>
        <Param Type="LVAR_TEXT_LABEL"/>
      </Params>
    </Command>
    <Command Name="IS_TEXT_LABEL_VAR_EQUAL_TO_TEXT_LABEL_LVAR">
      <Params>
        <Param Type="VAR_TEXT_LABEL"/>
        <Param Type="LVAR_TEXT_LABEL"/>
      </Params>
    </Command>
    <Command Name="DO_2D_LINES_INTERSECT">
      <Params>
        <Param Type="INPUT_FLOAT"/>
        <Param Type="INPUT_FLOAT"/>
        <Param Type="INPUT_FLOAT"/>
        <Param Type="INPUT_FLOAT"/>
        <Param Type="INPUT_FLOAT"/>
        <Param Type="INPUT_FLOAT"/>
        <Param Type="INPUT_FLOAT"/>
        <Param Type="INPUT_FLOAT"/>
      </Params>
    </Command>
    <Command Name="GET_2D_LINES_INTERSECT_POINT">
      <Params>
        <Param Type="INPUT_FLOAT"/>
        <Param Type="INPUT_FLOAT"/>
        <Param Type="INPUT_FLOAT"/>
        <Param Type="INPUT_FLOAT"/>
        <Param Type="INPUT_FLOAT"/>
        <Param Type="INPUT_FLOAT"/>
        <Param Type="INPUT_FLOAT"/>
        <Param Type="INPUT_FLOAT"/>
        <Param Type="OUTPUT_FLOAT"/>
        <Param Type="OUTPUT_FLOAT"/>
      </Params>
    </Command>
    <Command Name="IS_2D_POINT_IN_TRIANGLE">
      <Params>
        <Param Type="INPUT_FLOAT"/>
        <Param Type="INPUT_FLOAT"/>
        <Param Type="INPUT_FLOAT"/>
        <Param Type="INPUT_FLOAT"/>
        <Param Type="INPUT_FLOAT"/>
        <Param Type="INPUT_FLOAT"/>
        <Param Type="INPUT_FLOAT"/>
        <Param Type="INPUT_FLOAT"/>
      </Params>
    </Command>
    <Command Name="IS_2D_POINT_IN_RECTANGLE_ON_LEFT_SIDE_OF_LINE">
      <Params>
        <Param Type="INPUT_FLOAT"/>
        <Param Type="INPUT_FLOAT"/>
        <Param Type="INPUT_FLOAT"/>
        <Param Type="INPUT_FLOAT"/>
        <Param Type="INPUT_FLOAT"/>
        <Param Type="INPUT_FLOAT"/>
      </Params>
    </Command>
    <Command Name="IS_2D_POINT_ON_LEFT_SIDE_OF_2D_LINE">
      <Params>
        <Param Type="INPUT_FLOAT"/>
        <Param Type="INPUT_FLOAT"/>
        <Param Type="INPUT_FLOAT"/>
        <Param Type="INPUT_FLOAT"/>
        <Param Type="INPUT_FLOAT"/>
        <Param Type="INPUT_FLOAT"/>
      </Params>
    </Command>
    <Command Name="CHAR_LOOK_AT_OBJECT_ALWAYS">
      <Params>
        <Param Type="INPUT_INT"/>
        <Param Type="INPUT_INT"/>
      </Params>
    </Command>
    <Command Name="APPLY_COLLISION_ON_OBJECT">
      <Params>
        <Param Type="INPUT_INT"/>
        <Param Type="INPUT_FLOAT"/>
        <Param Type="INPUT_FLOAT"/>
        <Param Type="INPUT_FLOAT"/>
      </Params>
    </Command>
    <Command Name="SAVE_STRING_TO_DEBUG_FILE">
      <Params>
        <Param Type="TEXT_LABEL32"/>
        <Param Type="TEXT_LABEL32"/>
        <Param Type="TEXT_LABEL32"/>
        <Param Type="TEXT_LABEL32"/>
      </Params>
    </Command>
  </Commands>
  <Commands>
    <CommandId ID="1449" Name="IS_MISSION_SKIP"/>
    <CommandId ID="1450" Name="SET_IN_AMMUNATION"/>
    <CommandId ID="1451" Name="DO_SAVE_GAME"/>
    <CommandId ID="1452" Name="IS_RETRY"/>
    <CommandId ID="1453" Name="DUMMY"/>
    <CommandId ID="1454" Name="MARK_CUTSCENE_START"/>
    <CommandId ID="1455" Name="MARK_CUTSCENE_END"/>
    <CommandId ID="1456" Name="CUTSCENE_SCROLL"/>
    <CommandId ID="1457" Name="SET_LVAR_TEXT_LABEL_TO_LVAR_TEXT_LABEL"/>
    <CommandId ID="1458" Name="SET_VAR_TEXT_LABEL_TO_LVAR_TEXT_LABEL"/>
    <CommandId ID="1459" Name="SET_LVAR_TEXT_LABEL_TO_VAR_TEXT_LABEL"/>
    <CommandId ID="1460" Name="VAR_TEXT_LABEL"/>
    <CommandId ID="1461" Name="LVAR_TEXT_LABEL"/>
    <CommandId ID="1462" Name="IS_TEXT_LABEL_VAR_EQUAL_TO_TEXT_LABEL"/>
    <CommandId ID="1463" Name="IS_TEXT_LABEL_LVAR_EQUAL_TO_TEXT_LABEL"/>
    <CommandId ID="1464" Name="IS_TEXT_LABEL_VAR_EQUAL_TO_TEXT_LABEL_VAR"/>
    <CommandId ID="1465" Name="IS_TEXT_LABEL_LVAR_EQUAL_TO_TEXT_LABEL_LVAR"/>
    <CommandId ID="1466" Name="IS_TEXT_LABEL_VAR_EQUAL_TO_TEXT_LABEL_LVAR"/>
    <CommandId ID="1467" Name="DO_2D_LINES_INTERSECT"/>
    <CommandId ID="1468" Name="GET_2D_LINES_INTERSECT_POINT"/>
    <CommandId ID="1469" Name="IS_2D_POINT_IN_TRIANGLE"/>
    <CommandId ID="1470" Name="IS_2D_POINT_IN_RECTANGLE_ON_LEFT_SIDE_OF_LINE"/>
    <CommandId ID="1471" Name="IS_2D_POINT_ON_LEFT_SIDE_OF_2D_LINE"/>
    <CommandId ID="1472" Name="CHAR_LOOK_AT_OBJECT_ALWAYS"/>
    <CommandId ID="1473" Name="APPLY_COLLISION_ON_OBJECT"/>
    <CommandId ID="1474" Name="SAVE_STRING_TO_DEBUG_FILE"/>
  </Commands>
</GTA3Script>
